{
  "users": [
    {
      "id": "1",
      "name": "Vinicius",
      "email": "vini@email.com",
      "senha": "123456"
    },
    {
      "id": "2",
      "name": "Digão",
      "email": "digao@email.com",
      "senha": "456789"
    },
    {
      "id": "fd32",
      "name": "Bete Honorio",
      "email": "bete@email.com",
      "senha": "1234"
    },
    {
      "id": "e552",
      "name": "julia",
      "email": "ju@email.com",
      "senha": "123456"
    },
    {
      "id": "3c71",
      "name": "Teste",
      "email": "teste@email.com",
      "senha": "1234"
    },
    {
      "id": "6942",
      "name": "teste2",
      "email": "teste2@email.com",
      "senha": "12345"
    }
  ]
}